can_i_charge/__init__.py
can_i_charge/__main__.py
can_i_charge/cli.py
can_i_charge/exporter.py
can_i_charge-0.7.0.dist-info/licenses/LICENSE
can_i_charge-0.7.0.dist-info/METADATA
can_i_charge-0.7.0.dist-info/WHEEL
can_i_charge-0.7.0.dist-info/entry_points.txt
can_i_charge-0.7.0.dist-info/top_level.txt
can_i_charge-0.7.0.dist-info/RECORD
